gpusweep/__init__.py
gpusweep/binary_search.py
gpusweep/gpu_utils.py
gpusweep/grid_search.py
gpusweep/search_utils.py
gpusweep/configs/__init__.py
gpusweep/configs/base_experiment_config.py
gpusweep/configs/search_configs.py
gpusweep-0.0.2.dist-info/METADATA
gpusweep-0.0.2.dist-info/WHEEL
gpusweep-0.0.2.dist-info/top_level.txt
gpusweep-0.0.2.dist-info/RECORD
