Metadata-Version: 2.4
Name: gpusweep
Version: 0.0.2
Summary: GPU runner: binary/grid search over experiment configs with GPU scheduling
Requires-Python: >=3.10
Requires-Dist: torch>=2.1.0
Requires-Dist: numpy>=1.24.0
Requires-Dist: tqdm>=4.65.0
Requires-Dist: matplotlib>=3.7.0
Requires-Dist: PyYAML>=6.0.0
Requires-Dist: pandas>=2.0.0
Requires-Dist: pydrafig>=0.1.1
